Workbook

Sheet MSFT_Monthly
A1: date | B1: open | C1: high | D1: low | E1: close | F1: volume | G1: Return | H1: Rebase to 100 | I1: Peak | J1: Drawdown
A2: 43830 | B2: 151.81 | C2: 159.55 | D2: 146.64999 | E2: 157.7 | F2: 450303300 | H2: 100 | I2: 100
A3: 43861 | B3: 158.78 | C3: 174.05 | D3: 156.50999 | E3: 170.23 | F3: 558530000 | G3: =E3/E2-1 -> 0.079454661 | H3: =H2*(1+G3) -> 107.94547 | I3: =IF(H3>I2,H3,I2) -> 107.94547 | J3: =H3/I3-1 -> 0 | L3: Beta | M3: =SLOPE(G3:G62,SPY_Monthly!G3:G62) -> 0.87829949
A4: 43889 | B4: 170.42999 | C4: 190.7 | D4: 152 | E4: 162.00999 | F4: 887522300 | G4: =E4/E3-1 -> -0.048287643 | H4: =H3*(1+G4) -> 102.73303 | I4: =IF(H4>I3,H4,I3) -> 107.94547 | J4: =H4/I4-1 -> -0.048287643 | L4: MSFT 5Y Annualized return | M4: {=POWER(PRODUCT(1+G3:G62),1/5)-1} -> 0.21728754
A5: 43921 | B5: 165.31 | C5: 175 | D5: 132.52 | E5: 157.71001 | F5: 1612695500 | G5: =E5/E4-1 -> -0.026541477 | H5: =H4*(1+G5) -> 100.00635 | I5: =IF(H5>I4,H5,I4) -> 107.94547 | J5: =H5/I5-1 -> -0.073547495 | L5: SPY 5Y Annlualized Return | M5: {=POWER(PRODUCT(1+SPY_Monthly!G3:G62),1/5)-1} -> 0.12734796
A6: 43951 | B6: 153 | C6: 180.39999 | D6: 150.36 | E6: 179.21001 | F6: 984705000 | G6: =E6/E5-1 -> 0.13632616 | H6: =H5*(1+G6) -> 113.63983 | I6: =IF(H6>I5,H6,I5) -> 113.63983 | J6: =H6/I6-1 -> 0
A7: 43980 | B7: 175.8 | C7: 187.50999 | D7: 173.8 | E7: 183.25 | F7: 688845000 | G7: =E7/E6-1 -> 0.022543328 | H7: =H6*(1+G7) -> 116.20165 | I7: =IF(H7>I6,H7,I6) -> 116.20165 | J7: =H7/I7-1 -> 0 | L7: Max Drawdown | M7: =ABS(MIN(J3:J62)) -> 0.30979426
A8: 44012 | B8: 182.53999 | C8: 204.39999 | D8: 181.35001 | E8: 203.50999 | F8: 764965400 | G8: =E8/E7-1 -> 0.11055929 | H8: =H7*(1+G8) -> 129.04882 | I8: =IF(H8>I7,H8,I7) -> 129.04882 | J8: =H8/I8-1 -> 0
A9: 44043 | B9: 203.14 | C9: 216.38 | D9: 197.50999 | E9: 205.00999 | F9: 770190800 | G9: =E9/E8-1 -> 0.0073706677 | H9: =H8*(1+G9) -> 130 | I9: =IF(H9>I8,H9,I8) -> 130 | J9: =H9/I9-1 -> 0
A10: 44074 | B10: 211.52 | C10: 231.14999 | D10: 203.14 | E10: 225.53 | F10: 692423900 | G10: =E10/E9-1 -> 0.10009271 | H10: =H9*(1+G10) -> 143.01205 | I10: =IF(H10>I9,H10,I9) -> 143.01205 | J10: =H10/I10-1 -> 0
A11: 44104 | B11: 225.50999 | C11: 232.86 | D11: 196.25 | E11: 210.33 | F11: 768176300 | G11: =E11/E10-1 -> -0.067396799 | H11: =H10*(1+G11) -> 133.37349 | I11: =IF(H11>I10,H11,I10) -> 143.01205 | J11: =H11/I11-1 -> -0.067396799
A12: 44134 | B12: 213.49001 | C12: 225.21001 | D12: 199.62 | E12: 202.47 | F12: 631618000 | G12: =E12/E11-1 -> -0.037369847 | H12: =H11*(1+G12) -> 128.38935 | I12: =IF(H12>I11,H12,I11) -> 143.01205 | J12: =H12/I12-1 -> -0.10224804
A13: 44165 | B13: 204.28999 | C13: 228.12 | D13: 200.12 | E13: 214.07001 | F13: 573443000 | G13: =E13/E12-1 -> 0.057292473 | H13: =H12*(1+G13) -> 135.74509 | I13: =IF(H13>I12,H13,I12) -> 143.01205 | J13: =H13/I13-1 -> -0.050813608
A14: 44196 | B14: 214.50999 | C14: 227.17999 | D14: 209.11 | E14: 222.42 | F14: 594761700 | G14: =E14/E13-1 -> 0.039005899 | H14: =H13*(1+G14) -> 141.03995 | I14: =IF(H14>I13,H14,I13) -> 143.01205 | J14: =H14/I14-1 -> -0.01378974
A15: 44225 | B15: 222.53 | C15: 242.64 | D15: 211.94 | E15: 231.96001 | F15: 648076400 | G15: =E15/E14-1 -> 0.042891871 | H15: =H14*(1+G15) -> 147.08942 | I15: =IF(H15>I14,H15,I14) -> 147.08942 | J15: =H15/I15-1 -> 0
A16: 44253 | B16: 235.06 | C16: 246.13 | D16: 227.88 | E16: 232.38 | F16: 490962200 | G16: =E16/E15-1 -> 0.0018106138 | H16: =H15*(1+G16) -> 147.35574 | I16: =IF(H16>I15,H16,I15) -> 147.35574 | J16: =H16/I16-1 -> 0
A17: 44286 | B17: 235.89999 | C17: 241.05 | D17: 224.25999 | E17: 235.77 | F17: 724945800 | G17: =E17/E16-1 -> 0.014588175 | H17: =H16*(1+G17) -> 149.50539 | I17: =IF(H17>I16,H17,I16) -> 149.50539 | J17: =H17/I17-1 -> 0
A18: 44316 | B18: 238.47 | C18: 263.19 | D18: 238.05 | E18: 252.17999 | F18: 568661600 | G18: =E18/E17-1 -> 0.069601688 | H18: =H17*(1+G18) -> 159.91122 | I18: =IF(H18>I17,H18,I17) -> 159.91122 | J18: =H18/I18-1 -> 0
A19: 44344 | B19: 253.39999 | C19: 254.35001 | D19: 238.07001 | E19: 249.67999 | F19: 495084900 | G19: =E19/E18-1 -> -0.0099135542 | H19: =H18*(1+G19) -> 158.32593 | I19: =IF(H19>I18,H19,I18) -> 159.91122 | J19: =H19/I19-1 -> -0.0099135542
... A62: 45657 | B62: 421.57001 | C62: 456.16 | D62: 420.66 | E62: 421.5 | F62: 439902400 | G62: =E62/E61-1 -> -0.0046285128 | H62: =H61*(1+G62) -> 267.27964 | I62: =IF(H62>I61,H62,I61) -> 283.41789 | J62: =H62/I62-1 -> -0.056941513

Sheet MSFT_WACC
A1: Debt % | B1: Equity % | C1: D/E Ratio | D1: Cost of Debt | E1: Relevered Beta | F1: Cost of Equity | G1: WACC
A2: 0 | B2: 1 | C2: =A2/B2 -> 0 | D2: =4% -> 0.04 | E2: =$J$3*(1+(1-$J$4)*C2) -> 0.74748892 | F2: =$J$5+E2*(MSFT_Monthly!$M$5-MSFT_WACC!$J$5) -> 0.10529163 | I2: Assumed D/E at end of 2024 | J2: 0.25
A3: =A2+1% -> 0.01 | B3: =B2-0.01 -> 0.99 | C3: =A3/B3 -> 0.01010101 | D3: =D2+0.1% -> 0.041 | E3: =$J$3*(1+(1-$J$4)*C3) -> 0.7527742 | F3: =$J$5+E3*(MSFT_Monthly!$M$5-MSFT_WACC!$J$5) -> 0.10575329 | I3: Unlevered Beta | J3: =MSFT_Monthly!M3/(1+(1-MSFT_WACC!J4)*MSFT_WACC!J2) -> 0.74748892
A4: =A3+1% -> 0.02 | B4: =B3-0.01 -> 0.98 | C4: =A4/B4 -> 0.020408163 | D4: =D3+0.1% -> 0.042 | E4: =$J$3*(1+(1-$J$4)*C4) -> 0.75816734 | F4: =$J$5+E4*(MSFT_Monthly!$M$5-MSFT_WACC!$J$5) -> 0.10622437 | I4: Tax Rate | J4: 0.3
A5: =A4+1% -> 0.03 | B5: =B4-0.01 -> 0.97 | C5: =A5/B5 -> 0.030927835 | D5: =D4+0.1% -> 0.043 | E5: =$J$3*(1+(1-$J$4)*C5) -> 0.76367167 | F5: =$J$5+E5*(MSFT_Monthly!$M$5-MSFT_WACC!$J$5) -> 0.10670516 | I5: Risk Free Rate | J5: 0.04
A6: =A5+1% -> 0.04 | B6: =B5-0.01 -> 0.96 | C6: =A6/B6 -> 0.041666667 | D6: =D5+0.1% -> 0.044 | E6: =$J$3*(1+(1-$J$4)*C6) -> 0.76929068 | F6: =$J$5+E6*(MSFT_Monthly!$M$5-MSFT_WACC!$J$5) -> 0.10719597 | I6: Optimal WACC
A7: =A6+1% -> 0.05 | B7: =B6-0.01 -> 0.95 | C7: =A7/B7 -> 0.052631579 | D7: =D6+0.1% -> 0.045 | E7: =$J$3*(1+(1-$J$4)*C7) -> 0.77502799 | F7: =$J$5+E7*(MSFT_Monthly!$M$5-MSFT_WACC!$J$5) -> 0.10769712 | I7: Debt % at Optimal WACC
A8: =A7+1% -> 0.06 | B8: =B7-0.01 -> 0.94 | C8: =A8/B8 -> 0.063829787 | D8: =D7+0.1% -> 0.046 | E8: =$J$3*(1+(1-$J$4)*C8) -> 0.78088736 | F8: =$J$5+E8*(MSFT_Monthly!$M$5-MSFT_WACC!$J$5) -> 0.10820892
A9: =A8+1% -> 0.07 | B9: =B8-0.01 -> 0.93 | C9: =A9/B9 -> 0.075268817 | D9: =D8+0.1% -> 0.047 | E9: =$J$3*(1+(1-$J$4)*C9) -> 0.78687275 | F9: =$J$5+E9*(MSFT_Monthly!$M$5-MSFT_WACC!$J$5) -> 0.10873173
A10: =A9+1% -> 0.08 | B10: =B9-0.01 -> 0.92 | C10: =A10/B10 -> 0.086956522 | D10: =D9+0.1% -> 0.048 | E10: =$J$3*(1+(1-$J$4)*C10) -> 0.79298825 | F10: =$J$5+E10*(MSFT_Monthly!$M$5-MSFT_WACC!$J$5) -> 0.10926591
A11: =A10+1% -> 0.09 | B11: =B10-0.01 -> 0.91 | C11: =A11/B11 -> 0.098901099 | D11: =D10+0.1% -> 0.049 | E11: =$J$3*(1+(1-$J$4)*C11) -> 0.79923816 | F11: =$J$5+E11*(MSFT_Monthly!$M$5-MSFT_WACC!$J$5) -> 0.10981182
A12: =A11+1% -> 0.1 | B12: =B11-0.01 -> 0.9 | C12: =A12/B12 -> 0.11111111 | D12: =D11+0.1% -> 0.05 | E12: =$J$3*(1+(1-$J$4)*C12) -> 0.80562695 | F12: =$J$5+E12*(MSFT_Monthly!$M$5-MSFT_WACC!$J$5) -> 0.11036987
A13: =A12+1% -> 0.11 | B13: =B12-0.01 -> 0.89 | C13: =A13/B13 -> 0.12359551 | D13: =D12+0.1% -> 0.051 | E13: =$J$3*(1+(1-$J$4)*C13) -> 0.81215931 | F13: =$J$5+E13*(MSFT_Monthly!$M$5-MSFT_WACC!$J$5) -> 0.11094046
A14: =A13+1% -> 0.12 | B14: =B13-0.01 -> 0.88 | C14: =A14/B14 -> 0.13636364 | D14: =D13+0.1% -> 0.052 | E14: =$J$3*(1+(1-$J$4)*C14) -> 0.81884014 | F14: =$J$5+E14*(MSFT_Monthly!$M$5-MSFT_WACC!$J$5) -> 0.11152402
A15: =A14+1% -> 0.13 | B15: =B14-0.01 -> 0.87 | C15: =A15/B15 -> 0.14942529 | D15: =D14+0.1% -> 0.053 | E15: =$J$3*(1+(1-$J$4)*C15) -> 0.82567455 | F15: =$J$5+E15*(MSFT_Monthly!$M$5-MSFT_WACC!$J$5) -> 0.11212099
A16: =A15+1% -> 0.14 | B16: =B15-0.01 -> 0.86 | C16: =A16/B16 -> 0.1627907 | D16: =D15+0.1% -> 0.054 | E16: =$J$3*(1+(1-$J$4)*C16) -> 0.83266789 | F16: =$J$5+E16*(MSFT_Monthly!$M$5-MSFT_WACC!$J$5) -> 0.11273184
A17: =A16+1% -> 0.15 | B17: =B16-0.01 -> 0.85 | C17: =A17/B17 -> 0.17647059 | D17: =D16+0.1% -> 0.055 | E17: =$J$3*(1+(1-$J$4)*C17) -> 0.83982579 | F17: =$J$5+E17*(MSFT_Monthly!$M$5-MSFT_WACC!$J$5) -> 0.11335707
A18: =A17+1% -> 0.16 | B18: =B17-0.01 -> 0.84 | C18: =A18/B18 -> 0.19047619 | D18: =D17+0.1% -> 0.056 | E18: =$J$3*(1+(1-$J$4)*C18) -> 0.84715411 | F18: =$J$5+E18*(MSFT_Monthly!$M$5-MSFT_WACC!$J$5) -> 0.11399719
A19: =A18+1% -> 0.17 | B19: =B18-0.01 -> 0.83 | C19: =A19/B19 -> 0.20481928 | D19: =D18+0.1% -> 0.057 | E19: =$J$3*(1+(1-$J$4)*C19) -> 0.85465902 | F19: =$J$5+E19*(MSFT_Monthly!$M$5-MSFT_WACC!$J$5) -> 0.11465272
... A101: =A100+1% -> 0.99 | B101: =B100-0.01 -> 0.01 | C101: =A101/B101 -> 99 | D101: =D100+0.1% -> 0.139 | E101: =$J$3*(1+(1-$J$4)*C101) -> 52.548471 | F101: =$J$5+E101*(MSFT_Monthly!$M$5-MSFT_WACC!$J$5) -> 4.6300019

Sheet SPY_Monthly
A1: timestamp | B1: open | C1: high | D1: low | E1: close | F1: volume | G1: Return | H1: Peak | I1: Drawdown
A2: 43830 | B2: 314.59 | C2: 323.79999 | D2: 307.13 | E2: 321.85999 | F2: 1285175800 | H2: =MAX($E$2:E2) -> 321.85999 | I2: =(E2-H2)/H2 -> 0
A3: 43861 | B3: 323.54001 | C3: 332.95001 | D3: 320.35999 | E3: 321.73001 | F3: 1392003800 | G3: =E3/E2-1 -> -0.00040384019 | H3: =MAX($E$2:E3) -> 321.85999 | I3: =(E3-H3)/H3 -> -0.00040384019
A4: 43889 | B4: 323.35001 | C4: 339.07999 | D4: 285.54001 | E4: 296.26001 | F4: 2110214900 | G4: =E4/E3-1 -> -0.079165758 | H4: =MAX($E$2:E4) -> 321.85999 | I4: =(E4-H4)/H4 -> -0.079537628
A5: 43921 | B5: 298.20999 | C5: 313.84 | D5: 218.25999 | E5: 257.75 | F5: 5926017600 | G5: =E5/E4-1 -> -0.1299872 | H5: =MAX($E$2:E5) -> 321.85999 | I5: =(E5-H5)/H5 -> -0.19918596
A6: 43951 | B6: 247.98 | C6: 294.88 | D6: 243.89999 | E6: 290.48001 | F6: 2819312300 | G6: =E6/E5-1 -> 0.12698355 | H6: =MAX($E$2:E6) -> 321.85999 | I6: =(E6-H6)/H6 -> -0.097495747
A7: 43980 | B7: 285.31 | C7: 306.84 | D7: 272.98999 | E7: 304.32001 | F7: 1910460500 | G7: =E7/E6-1 -> 0.047645275 | H7: =MAX($E$2:E7) -> 321.85999 | I7: =(E7-H7)/H7 -> -0.054495683
A8: 44012 | B8: 303.62 | C8: 323.41 | D8: 296.73999 | E8: 308.35999 | F8: 2358674500 | G8: =E8/E7-1 -> 0.013275433 | H8: =MAX($E$2:E8) -> 321.85999 | I8: =(E8-H8)/H8 -> -0.041943704
A9: 44043 | B9: 309.57001 | C9: 327.23001 | D9: 309.07001 | E9: 326.51999 | F9: 1505145300 | G9: =E9/E8-1 -> 0.058892206 | H9: =MAX($E$2:E9) -> 326.51999 | I9: =(E9-H9)/H9 -> 0
A10: 44074 | B10: 328.32001 | C10: 351.29999 | D10: 327.73001 | E10: 349.31 | F10: 1045563300 | G10: =E10/E9-1 -> 0.069796676 | H10: =MAX($E$2:E10) -> 349.31 | I10: =(E10-H10)/H10 -> 0
A11: 44104 | B11: 350.20999 | C11: 358.75 | D11: 319.79999 | E11: 334.89001 | F11: 1814712700 | G11: =E11/E10-1 -> -0.041281355 | H11: =MAX($E$2:E11) -> 349.31 | I11: =(E11-H11)/H11 -> -0.041281355
A12: 44134 | B12: 337.69 | C12: 354.01999 | D12: 322.60001 | E12: 326.54001 | F12: 1629016100 | G12: =E12/E11-1 -> -0.02493356 | H12: =MAX($E$2:E12) -> 349.31 | I12: =(E12-H12)/H12 -> -0.065185623
A13: 44165 | B13: 330.20001 | C13: 364.38 | D13: 327.23999 | E13: 362.06 | F13: 1535244300 | G13: =E13/E12-1 -> 0.10877683 | H13: =MAX($E$2:E13) -> 362.06 | I13: =(E13-H13)/H13 -> 0
A14: 44196 | B14: 365.57001 | C14: 378.45999 | D14: 362.03 | E14: 373.88 | F14: 1344541500 | G14: =E14/E13-1 -> 0.032646528 | H14: =MAX($E$2:E14) -> 373.88 | I14: =(E14-H14)/H14 -> 0
... A62: 45657 | B62: 602.96997 | C62: 609.07001 | D62: 580.90997 | E62: 586.08002 | F62: 1059516700 | G62: =E62/E61-1 -> -0.027333787 | H62: =MAX($E$2:E62) -> 602.54999 | I62: =(E62-H62)/H62 -> -0.027333787
